[
  {
    "_id": 1,
    "name": "John Doe",
    "age": 30,
    "address": { "city": "New York", "state": "NY", "zip": "10001" },
    "contacts": [
      { "type": "email", "value": "john.doe@example.com" },
      { "type": "phone", "value": "+1 123-456-7890" }
    ],
    "skills": ["JavaScript", "Node.js", "MongoDB"],
    "projects": [
      { "title": "Project A", "contributors": ["Alice", "Bob"] },
      { "title": "Project B", "contributors": ["Charlie", "Diana"] }
    ]
  },
  {
    "_id": 2,
    "name": "Jane Smith",
    "age": 28,
    "address": { "city": "San Francisco", "state": "CA", "zip": "94105" },
    "contacts": [
      { "type": "email", "value": "jane.smith@example.com" },
      { "type": "phone", "value": "+1 987-654-3210" }
    ],
    "skills": ["Python", "Django", "PostgreSQL"],
    "projects": [
      { "title": "Project C", "contributors": ["Eve", "Frank"] },
      { "title": "Project D", "contributors": ["Grace", "Henry"] }
    ]
  },
  {
    "_id": 3,
    "name": "Bob Johnson",
    "age": 35,
    "address": { "city": "Chicago", "state": "IL", "zip": "60601" },
    "contacts": [
      { "type": "email", "value": "bob.johnson@example.com" },
      { "type": "phone", "value": "+1 555-123-4567" }
    ],
    "skills": ["Java", "Spring", "MySQL"],
    "projects": [
      { "title": "Project X", "contributors": ["Ivy", "Jack"] },
      { "title": "Project Y", "contributors": ["Kate", "Leo"] }
    ]
  },
  {
    "_id": 4,
    "name": "Alice Williams",
    "age": 25,
    "address": { "city": "Los Angeles", "state": "CA", "zip": "90001" },
    "contacts": [
      { "type": "email", "value": "alice.williams@example.com" },
      { "type": "phone", "value": "+1 333-999-8888" }
    ],
    "skills": ["C#", ".NET", "SQL Server"],
    "projects": [
      { "title": "Project M", "contributors": ["Nancy", "Oscar"] },
      { "title": "Project N", "contributors": ["Paul", "Quinn"] }
    ]
  },
  {
    "_id": 5,
    "name": "Charlie Brown",
    "age": 32,
    "address": { "city": "Seattle", "state": "WA", "zip": "98101" },
    "contacts": [
      { "type": "email", "value": "charlie.brown@example.com" },
      { "type": "phone", "value": "+1 777-555-1234" }
    ],
    "skills": ["Ruby", "Rails", "MongoDB"],
    "projects": [
      { "title": "Project R", "contributors": ["Rita", "Sam"] },
      { "title": "Project S", "contributors": ["Tom", "Uma"] }
    ]
  },
  {
    "_id": 6,
    "name": "Eva Davis",
    "age": 28,
    "address": { "city": "Boston", "state": "MA", "zip": "02101" },
    "contacts": [
      { "type": "email", "value": "eva.davis@example.com" },
      { "type": "phone", "value": "+1 111-222-3333" }
    ],
    "skills": ["Python", "Flask", "SQLite"],
    "projects": [
      { "title": "Project G", "contributors": ["Gary", "Holly"] },
      { "title": "Project H", "contributors": ["Ian", "Jill"] }
    ]
  },
  {
    "_id": 7,
    "name": "David White",
    "age": 40,
    "address": { "city": "Dallas", "state": "TX", "zip": "75201" },
    "contacts": [
      { "type": "email", "value": "david.white@example.com" },
      { "type": "phone", "value": "+1 999-444-7777" }
    ],
    "skills": ["JavaScript", "React", "Express"],
    "projects": [
      { "title": "Project J", "contributors": ["Katie", "Liam"] },
      { "title": "Project K", "contributors": ["Mike", "Nina"] }
    ]
  },
  {
    "_id": 8,
    "name": "Grace Moore",
    "age": 35,
    "address": { "city": "Miami", "state": "FL", "zip": "33101" },
    "contacts": [
      { "type": "email", "value": "grace.moore@example.com" },
      { "type": "phone", "value": "+1 777-333-2222" }
    ],
    "skills": ["Java", "Hibernate", "MySQL"],
    "projects": [
      { "title": "Project U", "contributors": ["Oliver", "Pam"] },
      { "title": "Project V", "contributors": ["Quincy", "Rose"] }
    ]
  },
  {
    "_id": 9,
    "name": "Frank Rodriguez",
    "age": 29,
    "address": { "city": "Houston", "state": "TX", "zip": "77001" },
    "contacts": [
      { "type": "email", "value": "frank.rodriguez@example.com" },
      { "type": "phone", "value": "+1 555-777-9999" }
    ],
    "skills": ["C++", "Qt", "SQLite"],
    "projects": [
      { "title": "Project W", "contributors": ["Sara", "Tim"] },
      { "title": "Project X", "contributors": ["Ursula", "Victor"] }
    ]
  },
  {
    "_id": 10,
    "name": "Ivy Green",
    "age": 27,
    "address": { "city": "Atlanta", "state": "GA", "zip": "30301" },
    "contacts": [
      { "type": "email", "value": "ivy.green@example.com" },
      { "type": "phone", "value": "+1 666-888-4444" }
    ],
    "skills": ["Ruby", "Sinatra", "PostgreSQL"],
    "projects": [
      { "title": "Project Y", "contributors": ["Walter", "Xena"] },
      { "title": "Project Z", "contributors": ["Yara", "Zane"] }
    ]
  }
]
